Workbook

Sheet Models
A1: Three Statement Financial Model
A3: Income Statement | B3: Year 1 | C3: Year 2 | D3: Year 3 | E3: Year 4 | F3: Year 5
A4: Revenue | B4: 100 | C4: =B4*(1+C5) -> 110 | D4: =C4*(1+D5) -> 118.8 | E4: =D4*(1+Models!E5) -> 128.304 | F4: =E4*(1+F5) -> 138.56832
A5: Revenue Growth | B5: 0 | C5: =Assumptions!C3 -> 0.1 | D5: =Assumptions!D3 -> 0.08 | E5: =Assumptions!E3 -> 0.08 | F5: =Assumptions!F3 -> 0.08
A6: EBITDA | B6: =B4*B7 -> 20 | C6: =C4*C7 -> 23.1 | D6: =D4*D7 -> 26.136 | E6: =E4*E7 -> 28.22688 | F6: =F4*F7 -> 30.48503
A7: EBITDA Margin | B7: =Assumptions!B4 -> 0.2 | C7: =Assumptions!C4 -> 0.21 | D7: =Assumptions!D4 -> 0.22 | E7: =Assumptions!E4 -> 0.22 | F7: =Assumptions!F4 -> 0.22
A8: Depreciation | B8: =B4*Assumptions!B5 -> 3 | C8: =C4*Assumptions!C5 -> 3.3 | D8: =D4*Assumptions!D5 -> 3.564 | E8: =E4*Assumptions!E5 -> 3.84912 | F8: =F4*Assumptions!F5 -> 4.1570496
A9: EBIT | B9: =B6-B8 -> 17 | C9: =C6-C8 -> 19.8 | D9: =D6-D8 -> 22.572 | E9: =E6-E8 -> 24.37776 | F9: =F6-F8 -> 26.327981
A10: Interest | B10: 5 | C10: =B10 -> 5 | D10: =C10 -> 5 | E10: =D10 -> 5 | F10: =E10 -> 5
A11: EBT | B11: =B9-B10 -> 12 | C11: =C9-C10 -> 14.8 | D11: =D9-D10 -> 17.572 | E11: =E9-E10 -> 19.37776 | F11: =F9-F10 -> 21.327981
A12: Tax | B12: =B11*Assumptions!B6 -> 3 | C12: =C11*Assumptions!C6 -> 3.7 | D12: =D11*Assumptions!D6 -> 4.393 | E12: =E11*Assumptions!E6 -> 4.84444 | F12: =F11*Assumptions!F6 -> 5.3319952
A13: Net Income | B13: =B11-B12 -> 9 | C13: =C11-C12 -> 11.1 | D13: =D11-D12 -> 13.179 | E13: =E11-E12 -> 14.53332 | F13: =F11-F12 -> 15.995986
A16: Balance Sheet | B16: Year 1 | C16: Year 2 | D16: Year 3 | E16: Year 4 | F16: Year 5
A17: Cash | B17: =Assumptions!B10+Models!B35 -> 28 | C17: =B17+C35 -> 37 | D17: =C17+D35 -> 48.111 | E17: =D17+E35 -> 60.41088 | F17: =E17+F35 -> 73.99475
A18: Working Capital | B18: =B4*Assumptions!B8 -> 10 | C18: =C4*Assumptions!C8 -> 11 | D18: =D4*Assumptions!D8 -> 11.88 | E18: =E4*Assumptions!E8 -> 12.8304 | F18: =F4*Assumptions!F8 -> 13.856832
A19: PP&E | B19: =Assumptions!B12-Models!B31-Models!B8 -> 31 | C19: =B19-C31-C8 -> 32.1 | D19: =C19-D31-D8 -> 33.288 | E19: =D19-E31-E8 -> 34.57104 | F19: =E19-F31-F8 -> 35.956723
A20: Total Assets | B20: =SUM(B17:B19) -> 69 | C20: =SUM(C17:C19) -> 80.1 | D20: =SUM(D17:D19) -> 93.279 | E20: =SUM(E17:E19) -> 107.81232 | F20: =SUM(F17:F19) -> 123.80831
A22: Debt | B22: 50 | C22: =B22 -> 50 | D22: =C22 -> 50 | E22: =D22 -> 50 | F22: =E22 -> 50
A23: Equity | B23: =Assumptions!B14+Models!B13 -> 19 | C23: =B23+C13 -> 30.1 | D23: =C23+D13 -> 43.279 | E23: =D23+E13 -> 57.81232 | F23: =E23+F13 -> 73.808306
A24: Total Liabilities & Equity | B24: =B22+B23 -> 69 | C24: =C22+C23 -> 80.1 | D24: =D22+D23 -> 93.279 | E24: =E22+E23 -> 107.81232 | F24: =F22+F23 -> 123.80831
A27: Cash Flow Statement | B27: Year 1 | C27: Year 2 | D27: Year 3 | E27: Year 4 | F27: Year 5
A28: Net Income | B28: =B13 -> 9 | C28: =C13 -> 11.1 | D28: =D13 -> 13.179 | E28: =E13 -> 14.53332 | F28: =F13 -> 15.995986
A29: Depreciation | B29: =B8 -> 3 | C29: =C8 -> 3.3 | D29: =D8 -> 3.564 | E29: =E8 -> 3.84912 | F29: =F8 -> 4.1570496
A30: Change in Working Capital | B30: =-(B18-Assumptions!B11) -> 0 | C30: =-(C18-B18) -> -1 | D30: =-(D18-C18) -> -0.88 | E30: =-(E18-D18) -> -0.9504 | F30: =-(F18-E18) -> -1.026432
A31: Capital Expenditure | B31: =-B4*Assumptions!B7 -> -4 | C31: =-C4*Assumptions!C7 -> -4.4 | D31: =-D4*Assumptions!D7 -> -4.752 | E31: =-E4*Assumptions!E7 -> -5.13216 | F31: =-F4*Assumptions!F7 -> -5.5427328
A32: Cash Flow From Operations | B32: =B28+B29+B30 -> 12 | C32: =C28+C29+C30 -> 13.4 | D32: =D28+D29+D30 -> 15.863 | E32: =E28+E29+E30 -> 17.43204 | F32: =F28+F29+F30 -> 19.126603
A33: Cash Flow from Investing | B33: =B31 -> -4 | C33: =C31 -> -4.4 | D33: =D31 -> -4.752 | E33: =E31 -> -5.13216 | F33: =F31 -> -5.5427328
A34: Cash Flow From Financing | B34: =0 -> 0 | C34: =0 -> 0 | D34: =0 -> 0 | E34: =0 -> 0 | F34: =0 -> 0
A35: Net Change in Cash | B35: =B32+B33+B34 -> 8 | C35: =C32+C33+C34 -> 9 | D35: =D32+D33+D34 -> 11.111 | E35: =E32+E33+E34 -> 12.29988 | F35: =F32+F33+F34 -> 13.58387

Sheet Assumptions
A1: Financial Model Assumptions
A2: Revenue Growth | B2: Year 1 | C2: Year 2 | D2: Year 3 | E2: Year 4 | F2: Year 5
B3: 0.1 | C3: 0.1 | D3: 0.08 | E3: 0.08 | F3: 0.08
A4: EBITDA Margin | B4: 0.2 | C4: 0.21 | D4: 0.22 | E4: 0.22 | F4: 0.22
A5: Depreciation (% Revenue) | B5: 0.03 | C5: 0.03 | D5: 0.03 | E5: 0.03 | F5: 0.03
A6: Tax Rate | B6: 0.25 | C6: 0.25 | D6: 0.25 | E6: 0.25 | F6: 0.25
A7: Capex (% Revenue) | B7: 0.04 | C7: 0.04 | D7: 0.04 | E7: 0.04 | F7: 0.04
A8: Working Capital (% Revenue) | B8: 0.1 | C8: 0.1 | D8: 0.1 | E8: 0.1 | F8: 0.1
A10: Opening Cash | B10: 20
A11: Opening Working Capital | B11: 10
A12: Opening PP&E | B12: 30
A13: Opening Debt | B13: 50
A14: Opening Equity | B14: =B10+B11+B12-B13 -> 10

Sheet Checks
A1: Model Checks
A3: Balance Sheet Check
A4: Year 1 | B4: Year 2 | C4: Year 3 | D4: Year 4 | E4: Year 5
A5: Balance Sheet Difference
A6: Status
A7: =Models!B20-Models!B24 -> 0 | B7: =Models!C20-Models!C24 -> 0 | C7: =Models!D20-Models!D24 -> 0 | D7: =Models!E20-Models!E24 -> 0 | E7: =Models!F20-Models!F24 -> 0
A8: =IF(ABS(A7)<0.1,"OK","CHECK") -> OK | B8: =IF(ABS(B7)<0.1,"OK","CHECK") -> OK | C8: =IF(ABS(C7)<0.1,"OK","CHECK") -> OK | D8: =IF(ABS(D7)<0.1,"OK","CHECK") -> OK | E8: =IF(ABS(E7)<0.1,"OK","CHECK") -> OK

Sheet DCF
A1: DCF valuation
B2: Year 1 | C2: Year 2 | D2: Year 3 | E2: Year 4 | F2: Year 5
A3: Revenue | B3: =Models!B4 -> 100 | C3: =Models!C4 -> 110 | D3: =Models!D4 -> 118.8 | E3: =Models!E4 -> 128.304 | F3: =Models!F4 -> 138.56832
A4: EBITDA | B4: =Models!B6 -> 20 | C4: =Models!C6 -> 23.1 | D4: =Models!D6 -> 26.136 | E4: =Models!E6 -> 28.22688 | F4: =Models!F6 -> 30.48503
A5: Depreciation | B5: =Models!B8 -> 3 | C5: =Models!C8 -> 3.3 | D5: =Models!D8 -> 3.564 | E5: =Models!E8 -> 3.84912 | F5: =Models!F8 -> 4.1570496
A6: EBIT | B6: =Models!B9 -> 17 | C6: =Models!C9 -> 19.8 | D6: =Models!D9 -> 22.572 | E6: =Models!E9 -> 24.37776 | F6: =Models!F9 -> 26.327981
A7: Tax on EBIT | B7: =B6*Assumptions!B6 -> 4.25 | C7: =C6*Assumptions!C6 -> 4.95 | D7: =D6*Assumptions!D6 -> 5.643 | E7: =E6*Assumptions!E6 -> 6.09444 | F7: =F6*Assumptions!F6 -> 6.5819952
A8: NOPAT | B8: =B6-B7 -> 12.75 | C8: =C6-C7 -> 14.85 | D8: =D6-D7 -> 16.929 | E8: =E6-E7 -> 18.28332 | F8: =F6-F7 -> 19.745986
A9: Depreciation | B9: =B5 -> 3 | C9: =C5 -> 3.3 | D9: =D5 -> 3.564 | E9: =E5 -> 3.84912 | F9: =F5 -> 4.1570496
A10: Capex | B10: =Models!B31 -> -4 | C10: =Models!C31 -> -4.4 | D10: =Models!D31 -> -4.752 | E10: =Models!E31 -> -5.13216 | F10: =Models!F31 -> -5.5427328
A11: Change in Working Capital | B11: =Models!B30 -> 0 | C11: =Models!C30 -> -1 | D11: =Models!D30 -> -0.88 | E11: =Models!E30 -> -0.9504 | F11: =Models!F30 -> -1.026432
A12: Free Cash Flow | B12: =B8+B9+B10-B11 -> 11.75 | C12: =C8+C9+C10-C11 -> 14.75 | D12: =D8+D9+D10-D11 -> 16.621 | E12: =E8+E9+E10-E11 -> 17.95068 | F12: =F8+F9+F10-F11 -> 19.386734
A15: DCF Assumptions
A16: WACC | B16: 0.1
A17: Terminal Growth Rate | B17: 0.025
A18: Net Debt | B18: 30
A20: Discout Factor | B20: =1/(1+$B$16)^1 -> 0.90909091 | C20: =1/(1+$B$16)^2 -> 0.82644628 | D20: =1/(1+$B$16)^3 -> 0.7513148 | E20: =1/(1+$B$16)^4 -> 0.68301346 | F20: =1/(1+$B$16)^5 -> 0.62092132
A21: Present Value of FCF | B21: =B12*B20 -> 10.681818 | C21: =C12*C20 -> 12.190083 | D21: =D12*D20 -> 12.487603 | E21: =E12*E20 -> 12.260556 | F21: =F12*F20 -> 12.037637
A23: Terminal Value | F23: =F12*(1+$B$17)/($B$16-$B$17) -> 264.95204
A24: PV of Terminal Value | F24: =F23*F20 -> 164.51437
A26: Enterprise Value | B26: =SUM(B21:F21)+F24 -> 224.17207
A27: Less: Net Debt | B27: =B18 -> 30
A28: Equity Value | B28: =B26-B27 -> 194.17207
A30: DCF Summary
A31: Enterprise Value | B31: =B26 -> 224.17207
A32: Net Debt | B32: =B27 -> 30
A33: Equity Value | B33: =B28 -> 194.17207
