Workbook

Sheet LBO
B3: Year 1 | C3: Year 2 | D3: Year 3 | E3: Year 4 | F3: Year 5
A4: Revenue | B4: 100 | C4: =B4*1.08 -> 108 | D4: =C4*1.08 -> 116.64 | E4: =D4*1.08 -> 125.9712 | F4: =E4*1.08 -> 136.0489
A5: EBITDA | B5: 30 | C5: =C4*30% -> 32.4 | D5: =D4*30% -> 34.992 | E5: =E4*30% -> 37.79136 | F5: =F4*30% -> 40.814669
A6: EBITDA Margin | B6: =B5/B4 -> 0.3 | C6: =C5/C4 -> 0.3 | D6: =D5/D4 -> 0.3 | E6: =E5/E4 -> 0.3 | F6: =F5/F4 -> 0.3
A7: Depreciation | B7: =B4*3% -> 3 | C7: =C4*3% -> 3.24 | D7: =D4*3% -> 3.4992 | E7: =E4*3% -> 3.779136 | F7: =F4*3% -> 4.0814669
A8: EBIT | B8: =B5-B7 -> 27 | C8: =C5-C7 -> 29.16 | D8: =D5-D7 -> 31.4928 | E8: =E5-E7 -> 34.012224 | F8: =F5-F7 -> 36.733202
A9: Interest expense | B9: =B19 -> 8.64 | C9: =C19 -> 6.72 | D9: =D19 -> 4.8 | E9: =E19 -> 2.88 | F9: =F19 -> 0.96
A10: EBT | B10: =B8-B9 -> 18.36 | C10: =C8-C9 -> 22.44 | D10: =D8-D9 -> 26.6928 | E10: =E8-E9 -> 31.132224 | F10: =F8-F9 -> 35.773202
A11: Taxes | B11: =B10*Assumptions!$B$12 -> 4.59 | C11: =C10*Assumptions!$B$12 -> 5.61 | D11: =D10*Assumptions!$B$12 -> 6.6732 | E11: =E10*Assumptions!$B$12 -> 7.783056 | F11: =F10*Assumptions!$B$12 -> 8.9433005
A12: Net Income | B12: =B10-B11 -> 13.77 | C12: =C10-C11 -> 16.83 | D12: =D10-D11 -> 20.0196 | E12: =E10-E11 -> 23.349168 | F12: =F10-F11 -> 26.829901
A15: Debt and Schedule
A16: Beginning Debt | B16: =Assumptions!B7 -> 120 | C16: =B18 -> 96 | D16: =C18 -> 72 | E16: =D18 -> 48 | F16: =E18 -> 24
A17: Debt Paydown | B17: =MIN(Assumptions!$B$7*Assumptions!$B$13,B16) -> 24 | C17: =MIN(Assumptions!$B$7*Assumptions!$B$13,C16) -> 24 | D17: =MIN(Assumptions!$B$7*Assumptions!$B$13,D16) -> 24 | E17: =MIN(Assumptions!$B$7*Assumptions!$B$13,E16) -> 24 | F17: =MIN(Assumptions!$B$7*Assumptions!$B$13,F16) -> 24
A18: Ending Debt | B18: =B16-B17 -> 96 | C18: =C16-C17 -> 72 | D18: =D16-D17 -> 48 | E18: =E16-E17 -> 24 | F18: =F16-F17 -> 0
A19: Interest expense | B19: =AVERAGE(B16,B18)*Assumptions!$B$11 -> 8.64 | C19: =AVERAGE(C16,C18)*Assumptions!$B$11 -> 6.72 | D19: =AVERAGE(D16,D18)*Assumptions!$B$11 -> 4.8 | E19: =AVERAGE(E16,E18)*Assumptions!$B$11 -> 2.88 | F19: =AVERAGE(F16,F18)*Assumptions!$B$11 -> 0.96
A22: Sponsor Returns
A24: Entry Sponsor Equity | B24: =Assumptions!B8 -> 120
A25: Exit Enterprise Value | B25: =F5*Assumptions!B9 -> 326.51735
A26: Exit Debt | B26: =F18 -> 0
A27: Exit Equity Value | B27: =B25-B26 -> 326.51735
A28: MOIC | B28: =B27/B24 -> 2.7209779
A29: IRR | B29: =(B27/B24)^(1/Assumptions!B10)-1 -> 0.22164495

Sheet Assumptions
A1: LBO Model Assumptions
A3: Entry EBITDA | B3: 30
A4: Entry EV/EBITDA | B4: 8
A5: Entry Enterprise Value | B5: =B3*B4 -> 240
A6: Debt/ EBITDA | B6: 4
A7: Entry Debt | B7: =B3*B6 -> 120
A8: Sponsor Equity | B8: =B5-B7 -> 120
A9: Exit EV/ EBITDA | B9: 8
A10: Holding Period | B10: 5
A11: Interest Rate | B11: 0.08
A12: Tax Rate | B12: 0.25
A13: Debt Paydown | B13: 0.2

Sheet Checks
A1: LBO Model Checks
A3: Entry EV Check | B3: =IF(Assumptions!B5=Assumptions!B3*Assumptions!B4,"OK","CHECK") -> OK
A4: Entry Debt Check | B4: =IF(Assumptions!B7=Assumptions!B3*Assumptions!B6,"OK","CHECK") -> OK
A5: Exit EV Check | B5: =IF(LBO!B25=LBO!F5*Assumptions!B9,"OK","CHECK") -> OK
A6: Exit Equity Check | B6: =IF(LBO!B27=LBO!B25-LBO!B26,"OK","CHECK") -> OK
